power_terminal/__init__.py
power_terminal/terminal.py
powerterminal-0.0.8.dist-info/LICENSE
powerterminal-0.0.8.dist-info/METADATA
powerterminal-0.0.8.dist-info/WHEEL
powerterminal-0.0.8.dist-info/top_level.txt
powerterminal-0.0.8.dist-info/RECORD
