Metadata-Version: 2.1
Name: powerterminal
Version: 0.0.8
Summary: Simple things that python should have out of the box.
Home-page: https://github.com/mathealgou/power_terminal
Author: Matheus Goulart
Author-email: mathealgou@gmail.com
License: UNKNOWN
Project-URL: Bug Tracker, https://github.com/mathealgou/power_terminal
Project-URL: Author, https://matheusgoulart.info
Platform: UNKNOWN
Classifier: Programming Language :: Python :: 3
Classifier: License :: OSI Approved :: MIT License
Classifier: Operating System :: OS Independent
Requires-Python: >=3.6
License-File: LICENSE
